{
"type": "FeatureCollection",
"name": "geo_47_看護小規模多機能型居宅介護（複合型サービス）",
"crs": { "type": "name", "properties": { "name": "urn:ogc:def:crs:OGC:1.3:CRS84" } },
"features": [
{ "type": "Feature", "properties": { "内容": "看護小規模多機能めぐみ小禄南【看護小規模多機能型居宅介護（複合型サービス）】沖縄県那覇市高良2丁目9番6号", "url": "https://www.kaigokensaku.mhlw.go.jp/47/index.php?action_kouhyou_detail_004_kani=true&JigyosyoCd=4790100640-00&ServiceCd=&Type=search", "url2": "https://megumi-care.com" }, "geometry": { "type": "Point", "coordinates": [ 127.661160391926998, 26.184416808716701 ] } },
{ "type": "Feature", "properties": { "内容": "看護小規模多機能型居宅介護末吉【看護小規模多機能型居宅介護（複合型サービス）】沖縄県那覇市首里末吉町2丁目95番4末吉ビル", "url": "https://www.kaigokensaku.mhlw.go.jp/47/index.php?action_kouhyou_detail_004_kani=true&JigyosyoCd=4790100624-00&ServiceCd=&Type=search", "url2": "http://nsleep.com" }, "geometry": { "type": "Point", "coordinates": [ 127.708427516171, 26.230728942470598 ] } },
{ "type": "Feature", "properties": { "内容": "看護小規模多機能型居宅介護　ナーシングケアハウスやえしま【看護小規模多機能型居宅介護（複合型サービス）】沖縄市八重島3丁目12番19号", "url": "https://www.kaigokensaku.mhlw.go.jp/47/index.php?action_kouhyou_detail_004_kani=true&JigyosyoCd=4790400248-00&ServiceCd=&Type=search", "url2": "https://www.kantaki-yaeshima.okinawa/" }, "geometry": { "type": "Point", "coordinates": [ 127.8055339, 26.3496164 ] } },
{ "type": "Feature", "properties": { "内容": "看護小規模多機能型居宅介護　愛貴【看護小規模多機能型居宅介護（複合型サービス）】沖縄県沖縄市字登川５６６番地なかがみ地域包括センター", "url": "https://www.kaigokensaku.mhlw.go.jp/47/index.php?action_kouhyou_detail_004_kani=true&JigyosyoCd=4790400289-00&ServiceCd=&Type=search", "url2": "http://www.nakagami.or.jp/" }, "geometry": { "type": "Point", "coordinates": [ 127.8265442, 26.3677927 ] } },
{ "type": "Feature", "properties": { "内容": "看護小規模多機能型居宅介護ゴン【看護小規模多機能型居宅介護（複合型サービス）】沖縄県宮古島市平良字西仲宗根1496-7看護小規模多機能型居宅介護ゴン", "url": "https://www.kaigokensaku.mhlw.go.jp/47/index.php?action_kouhyou_detail_004_kani=true&JigyosyoCd=4795500133-00&ServiceCd=&Type=search", "url2": "http://www.drgon.net/" }, "geometry": { "type": "Point", "coordinates": [ 125.3047877, 24.8095041 ] } },
{ "type": "Feature", "properties": { "内容": "看多機すこやか【看護小規模多機能型居宅介護（複合型サービス）】沖縄県宮古島市伊良部字長浜1320-1", "url": "https://www.kaigokensaku.mhlw.go.jp/47/index.php?action_kouhyou_detail_004_kani=true&JigyosyoCd=4795500182-00&ServiceCd=&Type=search", "url2": "https://yasuragi-sukoyaka.com/" }, "geometry": { "type": "Point", "coordinates": [ 125.1679521, 24.8351061 ] } },
{ "type": "Feature", "properties": { "内容": "ナーシングケアハウスぷくじ【看護小規模多機能型居宅介護（複合型サービス）】沖縄県国頭郡恩納村字恩納2858番地の3", "url": "https://www.kaigokensaku.mhlw.go.jp/47/index.php?action_kouhyou_detail_004_kani=true&JigyosyoCd=4791600028-00&ServiceCd=&Type=search", "url2": null }, "geometry": { "type": "Point", "coordinates": [ 127.852710102195005, 26.5014200488638 ] } },
{ "type": "Feature", "properties": { "内容": "ナーシングホームともいき【看護小規模多機能型居宅介護（複合型サービス）】沖縄県国頭郡金武町字金武10805番地", "url": "https://www.kaigokensaku.mhlw.go.jp/47/index.php?action_kouhyou_detail_004_kani=true&JigyosyoCd=4791800057-00&ServiceCd=&Type=search", "url2": "https://dream-kin.net/" }, "geometry": { "type": "Point", "coordinates": [ 127.938550155740998, 26.4631757793566 ] } },
{ "type": "Feature", "properties": { "内容": "看多機はなうい【看護小規模多機能型居宅介護（複合型サービス）】沖縄県中頭郡読谷村都屋245番地", "url": "https://www.kaigokensaku.mhlw.go.jp/47/index.php?action_kouhyou_detail_004_kani=true&JigyosyoCd=4792200109-00&ServiceCd=&Type=search", "url2": "https://www.hanauicare.com/" }, "geometry": { "type": "Point", "coordinates": [ 127.7280601, 26.3927781 ] } },
{ "type": "Feature", "properties": { "内容": "看護小規模多機能ホーム若松きたなかぐすく【看護小規模多機能型居宅介護（複合型サービス）】沖縄県中頭郡北中城村字安谷屋1346-1", "url": "https://www.kaigokensaku.mhlw.go.jp/47/index.php?action_kouhyou_detail_004_kani=true&JigyosyoCd=4792500011-00&ServiceCd=&Type=search", "url2": "http://www.agape-wakamatsu.or.jp" }, "geometry": { "type": "Point", "coordinates": [ 127.7930433, 26.2997866 ] } }
]
}
